discord/ext/ipc/__init__.py
discord/ext/ipc/client.py
discord/ext/ipc/errors.py
discord/ext/ipc/objects.py
discord/ext/ipc/server.py
Pycord_IPC-1.0.1.dist-info/LICENCE
Pycord_IPC-1.0.1.dist-info/METADATA
Pycord_IPC-1.0.1.dist-info/WHEEL
Pycord_IPC-1.0.1.dist-info/top_level.txt
Pycord_IPC-1.0.1.dist-info/RECORD
