Metadata-Version: 2.1
Name: Pycord-IPC
Version: 1.0.1
Summary: A high-performance inter-process communication library designed to work with the latest version of py-cord
Home-page: https://github.com/sampathgujarathi/pycord-ipc
Author: Sampath
Author-email: gujarathisampath@gmail.com
License: MIT License
Project-URL: Source, https://github.com/sampathgujarathi/pycord-ipc
Keywords: Pycord-IPC,ipc,python,py-cord
Classifier: Development Status :: 5 - Production/Stable
Classifier: Intended Audience :: Developers
Classifier: License :: OSI Approved :: MIT License
Classifier: Natural Language :: English
Classifier: Operating System :: OS Independent
Classifier: Programming Language :: Python
Classifier: Programming Language :: Python :: 3.8
Classifier: Programming Language :: Python :: 3.9
Classifier: Programming Language :: Python :: 3.10
Classifier: Topic :: Communications
Classifier: Topic :: Internet
Classifier: Topic :: Software Development
Classifier: Topic :: Software Development :: Libraries
Classifier: Topic :: Software Development :: Libraries :: Python Modules
Requires-Python: >=3.8.0
License-File: LICENCE
Requires-Dist: websockets >=10.4
Requires-Dist: py-cord >=2.4.1
